{
  "project_info": {
    "project_number": "1026723330569",
    "project_id": "clubs-8fea0",
    "storage_bucket": "clubs-8fea0.appspot.com"
  },
  "client": [
    {
      "client_info": {
        "mobilesdk_app_id": "1:1026723330569:android:930cd620ab65a9d62cd6d8",
        "android_client_info": {
          "package_name": "com.ritesh.clubs"
        }
      },
      "oauth_client": [],
      "api_key": [
        {
          "current_key": "AIzaSyAOZK7FruSK_HJTZuMZJhsISVUtxBzAFlA"
        }
      ],
      "services": {
        "appinvite_service": {
          "other_platform_oauth_client": []
        }
      }
    }
  ],
  "configuration_version": "1"
}